pyclock/__init__.py
pyclock/pyclock.py
digitalclock-0.8.4.dist-info/LICENSE
digitalclock-0.8.4.dist-info/METADATA
digitalclock-0.8.4.dist-info/WHEEL
digitalclock-0.8.4.dist-info/top_level.txt
digitalclock-0.8.4.dist-info/RECORD
