Metadata-Version: 2.1
Name: digitalclock
Version: 0.8.4
Summary: Seven segment display digital clock using Python tkinter
Home-page: https://gitlab.com/johncharlie/digitalclock
Author: Juan Carlos Perez Castellanos
Author-email: cuyopc@gmail.com
License: UNKNOWN
Platform: UNKNOWN
Classifier: Programming Language :: Python :: 2
Classifier: License :: OSI Approved :: GNU Affero General Public License v3
Classifier: Operating System :: Microsoft :: Windows
